{
  "group": "tempus",
  "type": "minecraft:crafting_shapeless",
  "ingredients": [
    {
      "item": "tempus:item_netherite_scrap"
    },
    {
      "item": "tempus:item_netherite_scrap"
    },
    {
      "item": "tempus:item_netherite_scrap"
    },
    {
      "item": "tempus:item_netherite_scrap"
    },
    {
      "item": "minecraft:gold_ingot"
    },
    {
      "item": "minecraft:gold_ingot"
    },
    {
      "item": "minecraft:gold_ingot"
    },
    {
      "item": "minecraft:gold_ingot"
    }
  ],
  "result": {
    "item": "tempus:item_netherite_ingot",
    "count": 1
  }
}